LICENSE
README.md
setup.py
x_open_point/__init__.py
x_open_point/main.py
x_open_point.egg-info/PKG-INFO
x_open_point.egg-info/SOURCES.txt
x_open_point.egg-info/dependency_links.txt
x_open_point.egg-info/entry_points.txt
x_open_point.egg-info/requires.txt
x_open_point.egg-info/top_level.txt